[
  {
    "user": "Phala-Network",
    "repo": "phala-blockchain",
    "timestamp": {
      "start": 1746243252781,
      "end": 1746243252781
    },
    "err": "\n   0: Cloning into '/tmp/os-checker-plugin-cargo/Phala-Network/phala-blockchain'...\n      Submodule 'standalone/prouter/i2pd' (https://github.com/Phala-Network/i2pd.git) registered for path 'standalone/prouter/i2pd'\n      Submodule 'subxt' (https://github.com/Phala-Network/substrate-subxt.git) registered for path 'subxt'\n      Cloning into '/tmp/os-checker-plugin-cargo/Phala-Network/phala-blockchain/standalone/prouter/i2pd'...\n      Cloning into '/tmp/os-checker-plugin-cargo/Phala-Network/phala-blockchain/subxt'...\n      Error: \n         0: resolution error: failed to find dependency: ark-transcript 0.0.2 (git+https://github.com/w3f/ring-vrf?rev=2019248)\n\n      Location:\n         src/layout/audit.rs:174\n\n        ━━━━━━━━━━━━━━━━━━━━━━━━━━━━━━━━━━ SPANTRACE ━━━━━━━━━━━━━━━━━━━━━━━━━━━━━━━━━━━\n\n         0: os_checker::layout::audit::cargo_audit with lock_file=Ok(\"/tmp/os-checker-plugin-cargo/Phala-Network/phala-blockchain/Cargo.lock\")\n            at src/layout/audit.rs:114\n\n      Backtrace omitted. Run with RUST_BACKTRACE=1 environment variable to display it.\n      Run with RUST_BACKTRACE=full to include source snippets.\n   0: \n\nLocation:\n   src/repo/os_checker.rs:27\n\n  ━━━━━━━━━━━━━━━━━━━━━━━━━━━━━━━━━━ SPANTRACE ━━━━━━━━━━━━━━━━━━━━━━━━━━━━━━━━━━━\n\n   0: os_checker_plugin_cargo::cache::cache with key=\"Api { branch: \\\"master\\\", sha: \\\"45b925eb1581de2b42eaa6c22537276dc691077e\\\" }\"\n      at src/cache/mod.rs:60\n   1: os_checker_plugin_cargo::list with user_repo=\"Phala-Network/phala-blockchain\"\n      at src/main.rs:16\n\nBacktrace omitted. Run with RUST_BACKTRACE=1 environment variable to display it.\nRun with RUST_BACKTRACE=full to include source snippets."
  },
  {
    "user": "informalsystems",
    "repo": "hermes",
    "timestamp": {
      "start": 1746243681003,
      "end": 1746243682033
    },
    "pkgs": {
      "ibc-chain-registry": {
        "version": "0.32.0",
        "dependencies": 14,
        "lib": true,
        "bin": false,
        "testcases": null,
        "tests": 0,
        "examples": 0,
        "benches": 0,
        "authors": [
          "Informal Systems <hello@informal.systems>"
        ],
        "description": "    Service to fetch data from the chain-registry\n",
        "documentation": null,
        "readme": null,
        "homepage": null,
        "keywords": [
          "cosmos",
          "ibc",
          "relayer",
          "chain",
          "registry"
        ],
        "categories": [],
        "rust_version": "1.83.0",
        "diag_total_count": null,
        "last_commit_time": "2025-04-17T06:59:00Z",
        "release_count": 27,
        "last_release_size": 71571,
        "last_release_time": "2025-04-17T07:13:39Z"
      },
      "ibc-relayer": {
        "version": "0.32.0",
        "dependencies": 75,
        "lib": true,
        "bin": false,
        "testcases": null,
        "tests": 0,
        "examples": 0,
        "benches": 0,
        "authors": [
          "Informal Systems <hello@informal.systems>"
        ],
        "description": "    Implementation of an IBC Relayer in Rust, as a library\n",
        "documentation": null,
        "readme": "README.md",
        "homepage": null,
        "keywords": [
          "blockchain",
          "consensus",
          "cosmos",
          "ibc",
          "tendermint"
        ],
        "categories": [],
        "rust_version": "1.83.0",
        "diag_total_count": null,
        "last_commit_time": "2025-04-17T06:59:00Z",
        "release_count": 60,
        "last_release_size": 349551,
        "last_release_time": "2025-04-17T07:05:56Z"
      },
      "ibc-relayer-cli": {
        "version": "1.13.0",
        "dependencies": 37,
        "lib": true,
        "bin": true,
        "testcases": null,
        "tests": 1,
        "examples": 0,
        "benches": 0,
        "authors": [
          "Informal Systems <hello@informal.systems>"
        ],
        "description": "  Hermes is an IBC Relayer written in Rust\n",
        "documentation": null,
        "readme": "README.md",
        "homepage": "https://hermes.informal.systems/",
        "keywords": [
          "blockchain",
          "consensus",
          "cosmos",
          "ibc",
          "tendermint"
        ],
        "categories": [],
        "rust_version": "1.83.0",
        "diag_total_count": null,
        "last_commit_time": "2025-04-17T06:59:00Z",
        "release_count": 59,
        "last_release_size": 145279,
        "last_release_time": "2025-04-17T07:17:52Z"
      },
      "ibc-relayer-rest": {
        "version": "0.32.0",
        "dependencies": 10,
        "lib": true,
        "bin": false,
        "testcases": null,
        "tests": 1,
        "examples": 0,
        "benches": 0,
        "authors": [
          "Informal Systems <hello@informal.systems>"
        ],
        "description": "  Rust implementation of a RESTful API server for Hermes\n",
        "documentation": null,
        "readme": "README.md",
        "homepage": "https://hermes.informal.systems/",
        "keywords": [
          "ibc",
          "rest",
          "api",
          "cosmos",
          "tendermint"
        ],
        "categories": [],
        "rust_version": "1.83.0",
        "diag_total_count": null,
        "last_commit_time": "2025-04-17T06:59:00Z",
        "release_count": 48,
        "last_release_size": 66441,
        "last_release_time": "2025-04-17T07:09:38Z"
      },
      "ibc-relayer-types": {
        "version": "0.32.0",
        "dependencies": 27,
        "lib": true,
        "bin": false,
        "testcases": null,
        "tests": 0,
        "examples": 0,
        "benches": 0,
        "authors": [
          "Informal Systems <hello@informal.systems>"
        ],
        "description": "    Implementation of the Inter-Blockchain Communication Protocol (IBC).\n    This crate comprises the main data structures and on-chain logic.\n",
        "documentation": null,
        "readme": "README.md",
        "homepage": null,
        "keywords": [
          "blockchain",
          "consensus",
          "cosmos",
          "ibc",
          "tendermint"
        ],
        "categories": [],
        "rust_version": "1.83.0",
        "diag_total_count": null,
        "last_commit_time": "2025-04-17T06:59:00Z",
        "release_count": 28,
        "last_release_size": 124104,
        "last_release_time": "2025-04-17T07:01:07Z"
      },
      "ibc-telemetry": {
        "version": "0.32.0",
        "dependencies": 13,
        "lib": true,
        "bin": false,
        "testcases": null,
        "tests": 0,
        "examples": 0,
        "benches": 0,
        "authors": [
          "Informal Systems <hello@informal.systems>"
        ],
        "description": "    Telemetry service for the Hermes IBC relayer\n",
        "documentation": null,
        "readme": "README.md",
        "homepage": null,
        "keywords": [
          "cosmos",
          "ibc",
          "relayer",
          "telemetry"
        ],
        "categories": [],
        "rust_version": "1.83.0",
        "diag_total_count": null,
        "last_commit_time": "2025-04-17T06:59:00Z",
        "release_count": 53,
        "last_release_size": 29997,
        "last_release_time": "2025-04-17T07:02:04Z"
      }
    }
  }
]